FlaskWebKaifaRumen/README.md
FlaskWebKaifaRumen/__init__.py
FlaskWebKaifaRumen/__main__.py
FlaskWebKaifaRumen/file.epub
FlaskWebKaifaRumen/index.html
FlaskWebKaifaRumen/css/__init__.py
FlaskWebKaifaRumen/css/annotations.css
FlaskWebKaifaRumen/css/main.css
FlaskWebKaifaRumen/css/normalize.css
FlaskWebKaifaRumen/css/popup.css
FlaskWebKaifaRumen/font/__init__.py
FlaskWebKaifaRumen/font/fontello.eot
FlaskWebKaifaRumen/font/fontello.svg
FlaskWebKaifaRumen/font/fontello.ttf
FlaskWebKaifaRumen/font/fontello.woff
FlaskWebKaifaRumen/img/__init__.py
FlaskWebKaifaRumen/img/annotator-glyph-sprite.png
FlaskWebKaifaRumen/img/annotator-icon-sprite.png
FlaskWebKaifaRumen/img/apple-touch-icon.png
FlaskWebKaifaRumen/img/cancelfullscreen.png
FlaskWebKaifaRumen/img/close.png
FlaskWebKaifaRumen/img/fullscreen.png
FlaskWebKaifaRumen/img/loader.gif
FlaskWebKaifaRumen/img/menu-icon.png
FlaskWebKaifaRumen/img/save.png
FlaskWebKaifaRumen/img/saved.png
FlaskWebKaifaRumen/img/settings-s.png
FlaskWebKaifaRumen/img/settings.png
FlaskWebKaifaRumen/img/star.png
FlaskWebKaifaRumen/js/__init__.py
FlaskWebKaifaRumen/js/epub.js
FlaskWebKaifaRumen/js/epub.min.js
FlaskWebKaifaRumen/js/epub.min.map
FlaskWebKaifaRumen/js/hooks.min.js
FlaskWebKaifaRumen/js/hooks.min.map
FlaskWebKaifaRumen/js/reader.js
FlaskWebKaifaRumen/js/reader.js.map
FlaskWebKaifaRumen/js/reader.min.js
FlaskWebKaifaRumen/js/reader.min.map
FlaskWebKaifaRumen/js/hooks/__init__.py
FlaskWebKaifaRumen/js/hooks/extensions/__init__.py
FlaskWebKaifaRumen/js/hooks/extensions/highlight.js
FlaskWebKaifaRumen/js/libs/__init__.py
FlaskWebKaifaRumen/js/libs/jquery.min.js
FlaskWebKaifaRumen/js/libs/localforage.min.js
FlaskWebKaifaRumen/js/libs/screenfull.js
FlaskWebKaifaRumen/js/libs/screenfull.min.js
FlaskWebKaifaRumen/js/libs/zip.min.js
FlaskWebKaifaRumen/js/plugins/__init__.py
FlaskWebKaifaRumen/js/plugins/hypothesis.js
FlaskWebKaifaRumen/js/plugins/search.js
flask_web_kaifa_rumen-2024.3.1.0.dist-info/METADATA
flask_web_kaifa_rumen-2024.3.1.0.dist-info/WHEEL
flask_web_kaifa_rumen-2024.3.1.0.dist-info/entry_points.txt
flask_web_kaifa_rumen-2024.3.1.0.dist-info/top_level.txt
flask_web_kaifa_rumen-2024.3.1.0.dist-info/RECORD
